[
    {
        "subject_code": "dentfn",
        "course_code": "501",
        "course_title": "HEAD & NECK ANATOMY",
        "sections": [
            {
                "restrictions": "Restr",
                "SLN": "13801",
                "section_id": "A",
                "credits": "3",
                "dates": "Th",
                "times": "830-1020",
                "building": "HST",
                "room": "T733",
                "instructor": "Rafferty,Katherine",
                "status": "Open",
                "enrollment": "55",
                "enrollment_limit": "55E",
                "grading": "",
                "course_fee": "",
                "modality": "B",
                "other": "F      130-520    *    *        Rafferty,Katherine\r\nFRIDAY SESSIONS ARE HELD IN HFF LAB\r\n.\r\nEXACT ROOM NUMBER TBD",
                "raw_string": "\nRestr  13801 A  3       Th     830-1020   HST  T733     Rafferty,Katherine         Open     55/  55E               B     \r\n                        F      130-520    *    *        Rafferty,Katherine\n                        FRIDAY SESSIONS ARE HELD IN HFF LAB                                                                                                                 \r\n                        .                                                                                                                                                   \r\n                        EXACT ROOM NUMBER TBD                                                                                                                               \r\n"
            },
            {
                "restrictions": "Restr",
                "SLN": "13802",
                "section_id": "B",
                "credits": "3",
                "dates": "Th",
                "times": "830-1020",
                "building": "*",
                "room": "*",
                "instructor": "Rafferty,Katherine",
                "status": "Closed",
                "enrollment": "8",
                "enrollment_limit": "8E",
                "grading": "",
                "course_fee": "",
                "modality": "B",
                "other": "F      130-520    *    *        Rafferty,Katherine\r\nRIDE SECTION - COURSE TAUGHT IN\r\nSPOKANE.",
                "raw_string": "\nRestr  13802 B  3       Th     830-1020   *    *        Rafferty,Katherine         Closed    8/   8E               B     \r\n                        F      130-520    *    *        Rafferty,Katherine\n                        RIDE SECTION - COURSE TAUGHT IN                                                                                                                     \r\n                        SPOKANE.                                                                                                                                            \r\n"
            }
        ]
    },
    {
        "subject_code": "dentfn",
        "course_code": "510",
        "course_title": "MOL CEL DISEASE",
        "sections": [
            {
                "restrictions": "Restr",
                "SLN": "13803",
                "section_id": "A",
                "credits": "4",
                "dates": "MTTh",
                "times": "130-320",
                "building": "HST",
                "room": "T733",
                "instructor": "Chung,Whasun Oh",
                "status": "Open",
                "enrollment": "55",
                "enrollment_limit": "55E",
                "grading": "",
                "course_fee": "",
                "modality": "B",
                "other": "",
                "raw_string": "\nRestr  13803 A  4       MTTh   130-320    HST  T733     Chung,Whasun Oh            Open     55/  55E               B     \r\n"
            },
            {
                "restrictions": "Restr",
                "SLN": "13806",
                "section_id": "B",
                "credits": "4",
                "dates": "MTTh",
                "times": "130-320",
                "building": "*",
                "room": "*",
                "instructor": "Chung,Whasun Oh",
                "status": "Closed",
                "enrollment": "8",
                "enrollment_limit": "8E",
                "grading": "",
                "course_fee": "",
                "modality": "B",
                "other": "RIDE SECTION - COURSE TAUGHT IN\r\nSPOKANE.",
                "raw_string": "\nRestr  13806 B  4       MTTh   130-320    *    *        Chung,Whasun Oh            Closed    8/   8E               B     \r\n                        RIDE SECTION - COURSE TAUGHT IN                                                                                                                     \r\n                        SPOKANE.                                                                                                                                            \r\n"
            }
        ]
    },
    {
        "subject_code": "dentfn",
        "course_code": "511",
        "course_title": "INVDERS & DFNDERS",
        "sections": [
            {
                "restrictions": "Restr",
                "SLN": "13808",
                "section_id": "A",
                "credits": "5",
                "dates": "MTWTh",
                "times": "130-320",
                "building": "HST",
                "room": "T733",
                "instructor": "Chung,Whasun Oh",
                "status": "Open",
                "enrollment": "55",
                "enrollment_limit": "55E",
                "grading": "",
                "course_fee": "",
                "modality": "B",
                "other": "",
                "raw_string": "\nRestr  13808 A  5       MTWTh  130-320    HST  T733     Chung,Whasun Oh            Open     55/  55E               B     \r\n"
            },
            {
                "restrictions": "Restr",
                "SLN": "13809",
                "section_id": "AA",
                "credits": "QZ",
                "dates": "MTWTh",
                "times": "230-320",
                "building": "SOCC",
                "room": "-322",
                "instructor": "Chung,Whasun Oh",
                "status": "Open",
                "enrollment": "19",
                "enrollment_limit": "19E",
                "grading": "",
                "course_fee": "",
                "modality": "B",
                "other": "",
                "raw_string": "\nRestr  13809 AA  QZ     MTWTh  230-320    SOCC -322     Chung,Whasun Oh            Open     19/  19E               B     \r\n"
            },
            {
                "restrictions": "Restr",
                "SLN": "13810",
                "section_id": "AB",
                "credits": "QZ",
                "dates": "MTWTh",
                "times": "230-320",
                "building": "SOCC",
                "room": "-350",
                "instructor": "Chung,Whasun Oh",
                "status": "Open",
                "enrollment": "18",
                "enrollment_limit": "18E",
                "grading": "",
                "course_fee": "",
                "modality": "B",
                "other": "",
                "raw_string": "\nRestr  13810 AB  QZ     MTWTh  230-320    SOCC -350     Chung,Whasun Oh            Open     18/  18E               B     \r\n"
            },
            {
                "restrictions": "Restr",
                "SLN": "13811",
                "section_id": "AC",
                "credits": "QZ",
                "dates": "MTWTh",
                "times": "230-320",
                "building": "SOCC",
                "room": "342",
                "instructor": "Chung,Whasun Oh",
                "status": "Closed",
                "enrollment": "18",
                "enrollment_limit": "18E",
                "grading": "",
                "course_fee": "",
                "modality": "B",
                "other": "",
                "raw_string": "\nRestr  13811 AC  QZ     MTWTh  230-320    SOCC 342      Chung,Whasun Oh            Closed   18/  18E               B     \r\n"
            },
            {
                "restrictions": "Restr",
                "SLN": "13812",
                "section_id": "B",
                "credits": "5",
                "dates": "MTWTh",
                "times": "130-320",
                "building": "*",
                "room": "*",
                "instructor": "Chung,Whasun Oh",
                "status": "Closed",
                "enrollment": "8",
                "enrollment_limit": "8E",
                "grading": "",
                "course_fee": "",
                "modality": "B",
                "other": "RIDE SECTION - COURSE TAUGHT IN\r\nSPOKANE.",
                "raw_string": "\nRestr  13812 B  5       MTWTh  130-320    *    *        Chung,Whasun Oh            Closed    8/   8E               B     \r\n                        RIDE SECTION - COURSE TAUGHT IN                                                                                                                     \r\n                        SPOKANE.                                                                                                                                            \r\n"
            },
            {
                "restrictions": "Restr",
                "SLN": "13813",
                "section_id": "BA",
                "credits": "QZ",
                "dates": "MTWTh",
                "times": "230-320",
                "building": "*",
                "room": "*",
                "instructor": "Chung,Whasun Oh",
                "status": "Closed",
                "enrollment": "8",
                "enrollment_limit": "8E",
                "grading": "",
                "course_fee": "",
                "modality": "B",
                "other": "RIDE SECTION - COURSE TAUGHT IN\r\nSPOKANE.",
                "raw_string": "\nRestr  13813 BA  QZ     MTWTh  230-320    *    *        Chung,Whasun Oh            Closed    8/   8E               B     \r\n                        RIDE SECTION - COURSE TAUGHT IN                                                                                                                     \r\n                        SPOKANE.                                                                                                                                            \r\n"
            }
        ]
    },
    {
        "subject_code": "dentfn",
        "course_code": "512",
        "course_title": "FNDN OF DENTAL MED",
        "sections": [
            {
                "restrictions": "Restr",
                "SLN": "13814",
                "section_id": "A",
                "credits": "2",
                "dates": "M",
                "times": "730-1150",
                "building": "HST",
                "room": "T733",
                "instructor": "Doomes,Ashland S",
                "status": "Open",
                "enrollment": "55",
                "enrollment_limit": "55E",
                "grading": "",
                "course_fee": "",
                "modality": "B",
                "other": "W      130-520    HST  T733     Doomes,Ashland S",
                "raw_string": "\nRestr  13814 A  2       M      730-1150   HST  T733     Doomes,Ashland S           Open     55/  55E               B     \r\n                        W      130-520    HST  T733     Doomes,Ashland S\n"
            },
            {
                "restrictions": "Restr",
                "SLN": "13815",
                "section_id": "B",
                "credits": "2",
                "dates": "M",
                "times": "730-1150",
                "building": "*",
                "room": "*",
                "instructor": "Doomes,Ashland S",
                "status": "Closed",
                "enrollment": "8",
                "enrollment_limit": "8E",
                "grading": "",
                "course_fee": "",
                "modality": "B",
                "other": "W      130-520    *    *        Doomes,Ashland S\r\nRIDE SECTION - COURSE TAUGHT IN\r\nSPOKANE.",
                "raw_string": "\nRestr  13815 B  2       M      730-1150   *    *        Doomes,Ashland S           Closed    8/   8E               B     \r\n                        W      130-520    *    *        Doomes,Ashland S\n                        RIDE SECTION - COURSE TAUGHT IN                                                                                                                     \r\n                        SPOKANE.                                                                                                                                            \r\n"
            }
        ]
    },
    {
        "subject_code": "dentfn",
        "course_code": "513",
        "course_title": "ORAL MICROBIO",
        "sections": [
            {
                "restrictions": "Restr",
                "SLN": "13816",
                "section_id": "A",
                "credits": "2",
                "dates": "M",
                "times": "800-1150",
                "building": "HST",
                "room": "T-733",
                "instructor": "McLean,Jeffrey S",
                "status": "Closed",
                "enrollment": "55",
                "enrollment_limit": "55E",
                "grading": "",
                "course_fee": "",
                "modality": "B",
                "other": "",
                "raw_string": "\nRestr  13816 A  2       M      800-1150   HST  T-733    McLean,Jeffrey S           Closed   55/  55E               B     \r\n"
            },
            {
                "restrictions": "Restr",
                "SLN": "13817",
                "section_id": "B",
                "credits": "2",
                "dates": "M",
                "times": "800-1150",
                "building": "*",
                "room": "*",
                "instructor": "McLean,Jeffrey S",
                "status": "Closed",
                "enrollment": "8",
                "enrollment_limit": "8E",
                "grading": "",
                "course_fee": "",
                "modality": "B",
                "other": "RIDE SECTION - COURSE TAUGHT IN\r\nSPOKANE",
                "raw_string": "\nRestr  13817 B  2       M      800-1150   *    *        McLean,Jeffrey S           Closed    8/   8E               B     \r\n                        RIDE SECTION - COURSE TAUGHT IN                                                                                                                     \r\n                        SPOKANE                                                                                                                                             \r\n"
            }
        ]
    },
    {
        "subject_code": "dentfn",
        "course_code": "560",
        "course_title": "MIND BRAIN BEHAVIOR",
        "sections": [
            {
                "restrictions": "Restr",
                "SLN": "13818",
                "section_id": "A",
                "credits": "5",
                "dates": "MF",
                "times": "130-320",
                "building": "HSEB",
                "room": "325",
                "instructor": "Sharma,Malveeka",
                "status": "Open",
                "enrollment": "63",
                "enrollment_limit": "63E",
                "grading": "",
                "course_fee": "",
                "modality": "B",
                "other": "MTThF  330-520    HSEB 235      Sharma,Malveeka\r\nT      130-320    SOCC 301\r\nALSO MEETS IN HSEB 215 ON THURS\r\n1:30PM-3:20PM.",
                "raw_string": "\nRestr  13818 A  5       MF     130-320    HSEB 325      Sharma,Malveeka            Open     63/  63E               B     \r\n                        MTThF  330-520    HSEB 235      Sharma,Malveeka\n                        T      130-320    SOCC 301      \n                        ALSO MEETS IN HSEB 215 ON THURS                                                                                                                     \r\n                        1:30PM-3:20PM.                                                                                                                                      \r\n"
            }
        ]
    },
    {
        "subject_code": "dentfn",
        "course_code": "561",
        "course_title": "LIFECYCLE",
        "sections": [
            {
                "restrictions": "Restr",
                "SLN": "13821",
                "section_id": "A",
                "credits": "4",
                "dates": "MF",
                "times": "130-320",
                "building": "HSEB",
                "room": "325",
                "instructor": "Garcia,Elizabeth",
                "status": "Open",
                "enrollment": "63",
                "enrollment_limit": "63E",
                "grading": "",
                "course_fee": "",
                "modality": "B",
                "other": "MTThF  330-520    HSEB 235      Garcia,Elizabeth\r\nT      130-320    SOCC 301\r\nALSO MEETS IN HSEB 215 ON THURS\r\n1:30PM-3:20PM.",
                "raw_string": "\nRestr  13821 A  4       MF     130-320    HSEB 325      Garcia,Elizabeth           Open     63/  63E               B     \r\n                        MTThF  330-520    HSEB 235      Garcia,Elizabeth\n                        T      130-320    SOCC 301      \n                        ALSO MEETS IN HSEB 215 ON THURS                                                                                                                     \r\n                        1:30PM-3:20PM.                                                                                                                                      \r\n"
            }
        ]
    },
    {
        "subject_code": "dentfn",
        "course_code": "562",
        "course_title": "FNDNS DENTAL MED 3",
        "sections": [
            {
                "restrictions": "Restr",
                "SLN": "13824",
                "section_id": "A",
                "credits": "2",
                "dates": "F",
                "times": "730-950",
                "building": "SOCC",
                "room": "221",
                "instructor": "Espinoza,Kimberly",
                "status": "Open",
                "enrollment": "63",
                "enrollment_limit": "63E",
                "grading": "",
                "course_fee": "",
                "modality": "B",
                "other": "F      1000-1220  SOCC 221      Espinoza,Kimberly\r\nMEETS IN HSEB 225 FIRST 4 WEEKS.",
                "raw_string": "\nRestr  13824 A  2       F      730-950    SOCC 221      Espinoza,Kimberly          Open     63/  63E               B     \r\n                        F      1000-1220  SOCC 221      Espinoza,Kimberly\n                        MEETS IN HSEB 225 FIRST 4 WEEKS.                                                                                                                    \r\n"
            }
        ]
    }
]